mouth/__init__.py
mouth/__main__.py
mouth/errors.py
mouth/install.py
mouth/rest.py
mouth/service.py
mouth/upgrade.py
mouth/define/.git
mouth/define/README.md
mouth/define/locale.json
mouth/define/template.json
mouth/define/template_email.json
mouth/define/template_sms.json
mouth/records/__init__.py
mouth/records/locale.py
mouth/records/template.py
mouth/records/template_email.py
mouth/records/template_sms.py
mouth/upgrades/__init__.py
mouth/upgrades/v1_0_0_v2_1_0.py
mouth2_oc-2.2.1.dist-info/METADATA
mouth2_oc-2.2.1.dist-info/WHEEL
mouth2_oc-2.2.1.dist-info/entry_points.txt
mouth2_oc-2.2.1.dist-info/licenses/LICENSE
mouth2_oc-2.2.1.dist-info/RECORD
