Metadata-Version: 2.4
Name: mouth2_oc
Version: 2.2.1
Summary: Mouth contains a service to run outgoing communications like email and sms messages
Project-URL: Documentation, https://github.com/ouroboroscoding/mouth2
Project-URL: Source, https://github.com/ouroboroscoding/mouth2
Project-URL: Tracker, https://github.com/ouroboroscoding/mouth2/issues
Author-email: "Chris Nasr - Ouroboros Coding Inc." <chris@ouroboroscoding.com>
Maintainer-email: "Chris Nasr - Ouroboros Coding Inc." <chris@ouroboroscoding.com>
License-File: LICENSE
Requires-Python: >=3.10
Requires-Dist: body-oc<2.3,>=2.2.0
Requires-Dist: brain2-oc<2.5,>=2.4.0
Requires-Dist: config-oc<1.2,>=1.1.0
Requires-Dist: define-oc<1.1,>=1.0.5
Requires-Dist: email-smtp<1.1,>=1.0.1
Requires-Dist: namedredis<1.1,>=1.0.2
Requires-Dist: rest-mysql<1.3,>=1.2.5
Requires-Dist: tools-oc<1.3,>=1.2.5
Requires-Dist: twilio==9.4.1
Requires-Dist: undefined-oc<1.1,>=1.0.0
Requires-Dist: upgrade-oc<1.2,>=1.1.0
